_meta.py
_uav_fdm.cpython-37m-x86_64-linux-gnu.so
uav_fdm.py
uav_fdm-0.1.3.dist-info/METADATA
uav_fdm-0.1.3.dist-info/top_level.txt
uav_fdm-0.1.3.dist-info/WHEEL
uav_fdm-0.1.3.dist-info/RECORD
uav_fdm-0.1.3.dist-info/LICENSE
