Metadata-Version: 2.1
Name: uav-fdm
Version: 0.1.3
Summary: A UAV FDM model for sim
Home-page: https://sh.matthewgong.com/matt/cluster_uav_node
Author: Zheng GONG
Author-email: matt@matthewgong.com
License: Copyright (C) 2020 Zheng GONG
Keywords: SWIG,uav,fdm
Platform: UNKNOWN
Requires-Python: >=3.4
